./.flake8
./.gitignore
./LICENSE
./PKG-INFO
./README.md
./env_example.txt
./openproject_mcp.py
./pyproject.toml
./requirements.txt
./uv.lock
./.github/dependabot.yml
./.github/workflows/ci.yml
./.github/workflows/publish.yml
./.github/workflows/security.yml
./tests/__init__.py
./tests/test_basic.py
./tests/test_client.py
openproject_mcp-1.0.2.dist-info/METADATA
openproject_mcp-1.0.2.dist-info/WHEEL
openproject_mcp-1.0.2.dist-info/entry_points.txt
openproject_mcp-1.0.2.dist-info/licenses/LICENSE
openproject_mcp-1.0.2.dist-info/RECORD
