Metadata-Version: 2.4
Name: openproject-mcp
Version: 1.0.2
Summary: A Model Context Protocol (MCP) server for OpenProject API v3 integration
Author: cleanspin, AndyEverything
License: MIT
License-File: LICENSE
Keywords: api,mcp,openproject,project-management
Classifier: Development Status :: 4 - Beta
Classifier: Intended Audience :: Developers
Classifier: License :: OSI Approved :: MIT License
Classifier: Programming Language :: Python :: 3
Classifier: Programming Language :: Python :: 3.10
Classifier: Programming Language :: Python :: 3.11
Classifier: Programming Language :: Python :: 3.12
Classifier: Programming Language :: Python :: 3.13
Requires-Python: >=3.10
Requires-Dist: aiohttp>=3.8.0
Requires-Dist: certifi>=2022.0.0
Requires-Dist: mcp>=1.0.0
Requires-Dist: python-dotenv>=1.0.0
Provides-Extra: dev
Requires-Dist: black>=22.0.0; extra == 'dev'
Requires-Dist: cyclonedx-bom>=4.0.0; extra == 'dev'
Requires-Dist: flake8>=4.0.0; extra == 'dev'
Requires-Dist: pytest>=7.0.0; extra == 'dev'
